tingting.py
fc_bigdatazz-1.0.dist-info/METADATA
fc_bigdatazz-1.0.dist-info/WHEEL
fc_bigdatazz-1.0.dist-info/top_level.txt
fc_bigdatazz-1.0.dist-info/RECORD
