Metadata-Version: 2.1
Name: fc-bigdatazz
Version: 1.0
Summary: 大数据3
Home-page: UNKNOWN
Author: 大数据3
Author-email: 1478849004@qq.com
License: UNKNOWN
Platform: UNKNOWN
